webint_guests/__init__.py
webint_guests/templates/__init__.py
webint_guests/templates/guests.html
webint_guests/templates/signin.html
webint_guests/templates/signout.html
webint_guests-0.0.6.dist-info/METADATA
webint_guests-0.0.6.dist-info/entry_points.txt
webint_guests-0.0.6.dist-info/WHEEL
webint_guests-0.0.6.dist-info/RECORD
